sinusboard/__init__.py
sinusboard/__main__.py
sinusboard/client/__init__.py
sinusboard/server/__init__.py
sinusboard/server/static/css/index.css
sinusboard/server/static/images/headphones.svg
sinusboard/server/static/images/icon-192.png
sinusboard/server/static/images/icon-512.png
sinusboard/server/static/images/icon-64.png
sinusboard/server/static/images/icon-96.png
sinusboard/server/static/js/index.js
sinusboard/server/static/manifest.json
sinusboard/server/static/service-worker.js
sinusboard/server/templates/index.html
sinusboard-0.1.0.dist-info/WHEEL
sinusboard-0.1.0.dist-info/METADATA
sinusboard-0.1.0.dist-info/RECORD
